sced_matcher/__init__.py
sced_matcher/core.py
sced_matcher/matcher.py
sced_matcher-0.1.3.dist-info/licenses/LICENSE.txt
sced_matcher-0.1.3.dist-info/METADATA
sced_matcher-0.1.3.dist-info/WHEEL
sced_matcher-0.1.3.dist-info/top_level.txt
sced_matcher-0.1.3.dist-info/RECORD
